prisme/__init__.py
prisme/cli.py
prisme/py.typed
prisme/ci/__init__.py
prisme/ci/docker.py
prisme/ci/github.py
prisme/config/__init__.py
prisme/config/loader.py
prisme/config/schema.py
prisme/deploy/__init__.py
prisme/deploy/config.py
prisme/deploy/hetzner.py
prisme/devcontainer/__init__.py
prisme/devcontainer/config.py
prisme/devcontainer/generator.py
prisme/devcontainer/manager.py
prisme/docker/__init__.py
prisme/docker/compose.py
prisme/docker/manager.py
prisme/docker/production.py
prisme/docker/proxy.py
prisme/dx/__init__.py
prisme/dx/devcontainer.py
prisme/dx/docs.py
prisme/dx/precommit.py
prisme/generators/__init__.py
prisme/generators/base.py
prisme/generators/ci.py
prisme/generators/deploy.py
prisme/generators/docker.py
prisme/generators/backend/__init__.py
prisme/generators/backend/admin.py
prisme/generators/backend/alembic.py
prisme/generators/backend/api_key_auth.py
prisme/generators/backend/auth.py
prisme/generators/backend/graphql.py
prisme/generators/backend/mcp.py
prisme/generators/backend/models.py
prisme/generators/backend/rest.py
prisme/generators/backend/schemas.py
prisme/generators/backend/services.py
prisme/generators/frontend/__init__.py
prisme/generators/frontend/admin.py
prisme/generators/frontend/auth.py
prisme/generators/frontend/components.py
prisme/generators/frontend/dashboard.py
prisme/generators/frontend/design.py
prisme/generators/frontend/error_pages.py
prisme/generators/frontend/graphql_ops.py
prisme/generators/frontend/headless.py
prisme/generators/frontend/hooks.py
prisme/generators/frontend/pages.py
prisme/generators/frontend/profile.py
prisme/generators/frontend/router.py
prisme/generators/frontend/search.py
prisme/generators/frontend/types.py
prisme/generators/frontend/widgets.py
prisme/generators/infrastructure/__init__.py
prisme/generators/testing/__init__.py
prisme/generators/testing/backend.py
prisme/generators/testing/frontend.py
prisme/migration/__init__.py
prisme/migration/detector.py
prisme/migration/domain_v1_to_v2.py
prisme-2.4.2.dist-info/METADATA
prisme-2.4.2.dist-info/WHEEL
prisme-2.4.2.dist-info/entry_points.txt
prisme-2.4.2.dist-info/licenses/LICENSE
prisme-2.4.2.dist-info/RECORD
