Metadata-Version: 2.4
Name: prisme
Version: 2.4.2
Summary: Code generation framework for full-stack applications from Pydantic models
Project-URL: Homepage, https://github.com/Lasse-numerous/prisme
Project-URL: Documentation, https://prisme.readthedocs.io/
Project-URL: Repository, https://github.com/Lasse-numerous/prisme
Project-URL: Issues, https://github.com/Lasse-numerous/prisme/issues
Author: Prism Contributors
License-Expression: MIT
License-File: LICENSE
Keywords: code-generation,fastapi,graphql,pydantic,react
Classifier: Development Status :: 3 - Alpha
Classifier: Intended Audience :: Developers
Classifier: License :: OSI Approved :: MIT License
Classifier: Programming Language :: Python :: 3
Classifier: Programming Language :: Python :: 3.13
Classifier: Topic :: Software Development :: Code Generators
Classifier: Typing :: Typed
Requires-Python: >=3.13
Requires-Dist: click>=8.1
Requires-Dist: jinja2>=3.1
Requires-Dist: pydantic>=2.10
Requires-Dist: rich>=13.0
Provides-Extra: dev
Requires-Dist: mypy>=1.14; extra == 'dev'
Requires-Dist: pre-commit>=4.0; extra == 'dev'
Requires-Dist: pytest-asyncio>=0.24; extra == 'dev'
Requires-Dist: pytest-cov>=6.0; extra == 'dev'
Requires-Dist: pytest-timeout>=2.3; extra == 'dev'
Requires-Dist: pytest>=8.0; extra == 'dev'
Requires-Dist: python-semantic-release>=9.0; extra == 'dev'
Requires-Dist: ruff>=0.9; extra == 'dev'
Provides-Extra: docs
Requires-Dist: mkdocs-material>=9.5; extra == 'docs'
Requires-Dist: mkdocs-minify-plugin>=0.8; extra == 'docs'
Requires-Dist: mkdocs>=1.6; extra == 'docs'
Requires-Dist: mkdocstrings[python]>=0.24; extra == 'docs'
Requires-Dist: pygments>=2.17; extra == 'docs'
Requires-Dist: pymdown-extensions>=10.0; extra == 'docs'
